Metadata-Version: 1.1
Name: npimp
Version: 0.5
Summary: Notebook regulation daemon
Home-page: https://github.com/tomkukral/npimp/
Author: Tomáš Kukrál
Author-email: tomas.kukral@6shore.net
License: MIT
Download-URL: https://github.com/tomkukral/npimp/archive/v0.4.tar.gz
Platform: UNKNOWN
